{
  "generated_at": "2025-08-26T12:46:52.466828+00:00",
  "window_hours": 24,
  "totals": {
    "positive": 1297,
    "neutral": 451,
    "negative": 1413
  },
  "by_publication": [
    {
      "source": "Independent",
      "positive": 179,
      "neutral": 80,
      "negative": 229,
      "count": 488,
      "region": "Europe"
    },
    {
      "source": "The Hindu",
      "positive": 124,
      "neutral": 77,
      "negative": 96,
      "count": 297,
      "region": "Asia-Pacific"
    },
    {
      "source": "Bloomberg",
      "positive": 113,
      "neutral": 24,
      "negative": 76,
      "count": 213,
      "region": "Business"
    },
    {
      "source": "Channel News Asia",
      "positive": 61,
      "neutral": 53,
      "negative": 42,
      "count": 156,
      "region": "Asia-Pacific"
    },
    {
      "source": "Times of India",
      "positive": 63,
      "neutral": 15,
      "negative": 69,
      "count": 147,
      "region": "Asia-Pacific"
    },
    {
      "source": "The Guardian",
      "positive": 43,
      "neutral": 6,
      "negative": 89,
      "count": 138,
      "region": "Europe"
    },
    {
      "source": "CBS News",
      "positive": 49,
      "neutral": 17,
      "negative": 70,
      "count": 136,
      "region": "North America"
    },
    {
      "source": "Australian Broadcasting Corporation",
      "positive": 50,
      "neutral": 8,
      "negative": 78,
      "count": 136,
      "region": "Asia-Pacific"
    },
    {
      "source": "Fox News",
      "positive": 38,
      "neutral": 12,
      "negative": 67,
      "count": 117,
      "region": "North America"
    },
    {
      "source": "South China Morning Post",
      "positive": 56,
      "neutral": 4,
      "negative": 33,
      "count": 93,
      "region": "Asia-Pacific"
    },
    {
      "source": "AllAfrica",
      "positive": 41,
      "neutral": 6,
      "negative": 38,
      "count": 85,
      "region": "Africa"
    },
    {
      "source": "BBC News",
      "positive": 44,
      "neutral": 5,
      "negative": 34,
      "count": 83,
      "region": "Global"
    },
    {
      "source": "NBC News",
      "positive": 20,
      "neutral": 8,
      "negative": 53,
      "count": 81,
      "region": "North America"
    },
    {
      "source": "Al Jazeera English",
      "positive": 17,
      "neutral": 7,
      "negative": 54,
      "count": 78,
      "region": "Middle East"
    },
    {
      "source": "BBC Sport",
      "positive": 56,
      "neutral": 7,
      "negative": 9,
      "count": 72,
      "region": "Sports"
    },
    {
      "source": "France 24",
      "positive": 17,
      "neutral": 2,
      "negative": 49,
      "count": 68,
      "region": "Europe"
    },
    {
      "source": "Euronews",
      "positive": 32,
      "neutral": 5,
      "negative": 27,
      "count": 64,
      "region": "Europe"
    },
    {
      "source": "ESPN",
      "positive": 36,
      "neutral": 12,
      "negative": 14,
      "count": 62,
      "region": "Global"
    },
    {
      "source": "Sky Sports",
      "positive": 22,
      "neutral": 17,
      "negative": 16,
      "count": 55,
      "region": "Sports"
    },
    {
      "source": "Middle East Eye",
      "positive": 5,
      "neutral": 0,
      "negative": 50,
      "count": 55,
      "region": "Middle East"
    },
    {
      "source": "CNBC",
      "positive": 20,
      "neutral": 17,
      "negative": 18,
      "count": 55,
      "region": "Business"
    },
    {
      "source": "Mashable",
      "positive": 36,
      "neutral": 11,
      "negative": 4,
      "count": 51,
      "region": "Technology"
    },
    {
      "source": "Straits Times",
      "positive": 17,
      "neutral": 7,
      "negative": 15,
      "count": 39,
      "region": "Asia-Pacific"
    },
    {
      "source": "MarketWatch",
      "positive": 15,
      "neutral": 7,
      "negative": 14,
      "count": 36,
      "region": "Business"
    },
    {
      "source": "Financial Times",
      "positive": 10,
      "neutral": 4,
      "negative": 18,
      "count": 32,
      "region": "Europe"
    },
    {
      "source": "Times of Israel",
      "positive": 9,
      "neutral": 0,
      "negative": 23,
      "count": 32,
      "region": "Middle East"
    },
    {
      "source": "Irish Times",
      "positive": 11,
      "neutral": 8,
      "negative": 12,
      "count": 31,
      "region": "Europe"
    },
    {
      "source": "RT News",
      "positive": 12,
      "neutral": 4,
      "negative": 10,
      "count": 26,
      "region": "Europe"
    },
    {
      "source": "New York Times",
      "positive": 6,
      "neutral": 0,
      "negative": 20,
      "count": 26,
      "region": "North America"
    },
    {
      "source": "NPR",
      "positive": 3,
      "neutral": 3,
      "negative": 18,
      "count": 24,
      "region": "North America"
    },
    {
      "source": "Engadget",
      "positive": 20,
      "neutral": 1,
      "negative": 3,
      "count": 24,
      "region": "Technology"
    },
    {
      "source": "ABC News",
      "positive": 4,
      "neutral": 5,
      "negative": 13,
      "count": 22,
      "region": "North America"
    },
    {
      "source": "Deutsche Welle",
      "positive": 9,
      "neutral": 3,
      "negative": 8,
      "count": 20,
      "region": "Europe"
    },
    {
      "source": "Wired",
      "positive": 15,
      "neutral": 2,
      "negative": 3,
      "count": 20,
      "region": "Technology"
    },
    {
      "source": "The Verge",
      "positive": 12,
      "neutral": 0,
      "negative": 6,
      "count": 18,
      "region": "Technology"
    },
    {
      "source": "Sputnik News",
      "positive": 10,
      "neutral": 2,
      "negative": 5,
      "count": 17,
      "region": "Europe"
    },
    {
      "source": "Daily News Egypt",
      "positive": 9,
      "neutral": 2,
      "negative": 4,
      "count": 15,
      "region": "North America"
    },
    {
      "source": "Ars Technica",
      "positive": 2,
      "neutral": 3,
      "negative": 8,
      "count": 13,
      "region": "North America"
    },
    {
      "source": "Sky News",
      "positive": 2,
      "neutral": 2,
      "negative": 9,
      "count": 13,
      "region": "Middle East"
    },
    {
      "source": "Telegraph",
      "positive": 5,
      "neutral": 4,
      "negative": 3,
      "count": 12,
      "region": "North America"
    },
    {
      "source": "Washington Post",
      "positive": 2,
      "neutral": 1,
      "negative": 4,
      "count": 7,
      "region": "North America"
    },
    {
      "source": "Buenos Aires Herald",
      "positive": 2,
      "neutral": 0,
      "negative": 2,
      "count": 4,
      "region": "South America"
    }
  ],
  "by_region": [
    {
      "region": "North America",
      "positive": 477,
      "neutral": 161,
      "negative": 593,
      "count": 1231
    },
    {
      "region": "Asia-Pacific",
      "positive": 333,
      "neutral": 117,
      "negative": 286,
      "count": 736
    },
    {
      "region": "Europe",
      "positive": 267,
      "neutral": 97,
      "negative": 237,
      "count": 601
    },
    {
      "region": "Middle East",
      "positive": 46,
      "neutral": 6,
      "negative": 186,
      "count": 238
    },
    {
      "region": "Global",
      "positive": 108,
      "neutral": 53,
      "negative": 62,
      "count": 223
    },
    {
      "region": "Africa",
      "positive": 17,
      "neutral": 4,
      "negative": 22,
      "count": 43
    },
    {
      "region": "Business",
      "positive": 18,
      "neutral": 6,
      "negative": 11,
      "count": 35
    },
    {
      "region": "South America",
      "positive": 9,
      "neutral": 2,
      "negative": 12,
      "count": 23
    },
    {
      "region": "Technology",
      "positive": 14,
      "neutral": 1,
      "negative": 2,
      "count": 17
    },
    {
      "region": "Sports",
      "positive": 8,
      "neutral": 4,
      "negative": 2,
      "count": 14
    }
  ],
  "by_topic": [
    {
      "topic": "Tech",
      "positive": 282,
      "neutral": 123,
      "negative": 346,
      "count": 751
    },
    {
      "topic": "Politics",
      "positive": 261,
      "neutral": 77,
      "negative": 354,
      "count": 692
    },
    {
      "topic": "Other",
      "positive": 229,
      "neutral": 97,
      "negative": 225,
      "count": 551
    },
    {
      "topic": "World",
      "positive": 105,
      "neutral": 39,
      "negative": 214,
      "count": 358
    },
    {
      "topic": "Business",
      "positive": 124,
      "neutral": 41,
      "negative": 56,
      "count": 221
    },
    {
      "topic": "Sports",
      "positive": 147,
      "neutral": 30,
      "negative": 38,
      "count": 215
    },
    {
      "topic": "Entertainment",
      "positive": 43,
      "neutral": 18,
      "negative": 34,
      "count": 95
    },
    {
      "topic": "Health",
      "positive": 28,
      "neutral": 6,
      "negative": 50,
      "count": 84
    },
    {
      "topic": "Regional",
      "positive": 33,
      "neutral": 6,
      "negative": 36,
      "count": 75
    },
    {
      "topic": "Local",
      "positive": 19,
      "neutral": 4,
      "negative": 38,
      "count": 61
    },
    {
      "topic": "Science",
      "positive": 26,
      "neutral": 10,
      "negative": 22,
      "count": 58
    }
  ],
  "sample_headlines": [
    {
      "title": "Keppel files for S$68.4 million claim against Seatrium over Brazil corruption case",
      "url": "https://www.channelnewsasia.com/business/keppel-files-claim-against-seatrium-brazil-corruption-5315111",
      "source": "Channel News Asia",
      "region": "South America",
      "published": "2025-08-26T20:36:00+08:00",
      "sentiment": "negative"
    },
    {
      "title": "Dollar falls as Trump's move to fire Fed governor spooks investors",
      "url": "https://www.channelnewsasia.com/business/dollar-falls-trumps-move-fire-fed-governor-spooks-investors-5314001",
      "source": "Channel News Asia",
      "region": "Global",
      "published": "2025-08-26T20:20:42+08:00",
      "sentiment": "negative"
    },
    {
      "title": "Man who raped stepdaughter gets 24 years\u2019 jail, 24 strokes of the cane",
      "url": "https://www.straitstimes.com/singapore/courts-crime/man-who-raped-stepdaughter-gets-24-years-jail-24-strokes-of-the-cane",
      "source": "Straits Times",
      "region": "Global",
      "published": "2025-08-26T20:10:00+08:00",
      "sentiment": "negative"
    },
    {
      "title": "The green transition needs a commercial case for it: Panellists",
      "url": "https://www.straitstimes.com/singapore/the-green-transition-needs-a-commercial-case-for-it-panellists",
      "source": "Straits Times",
      "region": "Global",
      "published": "2025-08-26T19:50:00+08:00",
      "sentiment": "neutral"
    },
    {
      "title": "Cross-country skiing-No pressure, no regrets as Pellegrino eyes home Olympics last dance",
      "url": "https://www.channelnewsasia.com/sport/cross-country-skiing-no-pressure-no-regrets-pellegrino-eyes-home-olympics-last-dance-5315076",
      "source": "Channel News Asia",
      "region": "Global",
      "published": "2025-08-26T19:48:13+08:00",
      "sentiment": "neutral"
    },
    {
      "title": "Nvidia results to spotlight fallout of China-US trade war",
      "url": "https://www.channelnewsasia.com/business/us-china-trade-war-nvidia-earnings-results-5314846",
      "source": "Channel News Asia",
      "region": "North America",
      "published": "2025-08-26T19:48:00+08:00",
      "sentiment": "negative"
    },
    {
      "title": "Japan proposes 10-year extension for offshore wind farm leases to ease cost pressures",
      "url": "https://www.channelnewsasia.com/business/japan-proposes-10-year-extension-offshore-wind-farm-leases-ease-cost-pressures-5315086",
      "source": "Channel News Asia",
      "region": "Asia-Pacific",
      "published": "2025-08-26T19:47:56+08:00",
      "sentiment": "positive"
    },
    {
      "title": "Cadillac F1 shut down speculation about possible Horner move",
      "url": "https://www.channelnewsasia.com/sport/cadillac-f1-shut-down-speculation-about-possible-horner-move-5315061",
      "source": "Channel News Asia",
      "region": "Global",
      "published": "2025-08-26T19:40:34+08:00",
      "sentiment": "neutral"
    },
    {
      "title": "Fears of new political crisis grip France",
      "url": "https://www.channelnewsasia.com/world/france-political-fears-francois-bayrou-confidence-vote-5315021",
      "source": "Channel News Asia",
      "region": "Europe",
      "published": "2025-08-26T19:40:22+08:00",
      "sentiment": "negative"
    },
    {
      "title": "Maid given 9 months\u2019 jail for hitting seven-month-old baby",
      "url": "https://www.straitstimes.com/singapore/courts-crime/maid-jailed-for-9-months-for-hitting-seven-month-old-baby",
      "source": "Straits Times",
      "region": "Global",
      "published": "2025-08-26T19:40:00+08:00",
      "sentiment": "neutral"
    },
    {
      "title": "Cadillac sign Perez and Bottas as F1 team's debut lineup",
      "url": "https://www.channelnewsasia.com/sport/cadillac-sign-perez-and-bottas-f1-teams-debut-lineup-5315066",
      "source": "Channel News Asia",
      "region": "Global",
      "published": "2025-08-26T19:38:50+08:00",
      "sentiment": "neutral"
    },
    {
      "title": "PetroChina to buy natural gas facilities from controlling shareholder in $5.59 billion deal",
      "url": "https://www.channelnewsasia.com/business/petrochina-buy-natural-gas-facilities-controlling-shareholder-559-billion-deal-5315006",
      "source": "Channel News Asia",
      "region": "Asia-Pacific",
      "published": "2025-08-26T19:26:37+08:00",
      "sentiment": "positive"
    },
    {
      "title": "No impact on Singapore buildings from recent Johor earthquake: BCA",
      "url": "https://www.straitstimes.com/singapore/no-impact-on-singapore-buildings-from-recent-johor-earthquake-bca",
      "source": "Straits Times",
      "region": "Asia-Pacific",
      "published": "2025-08-26T19:23:18+08:00",
      "sentiment": "negative"
    },
    {
      "title": "Maid gets jail for hitting 7-month-old baby repeatedly, leaving bruise",
      "url": "https://www.channelnewsasia.com/singapore/maid-jailed-hitting-seven-month-baby-repeatedly-leaving-bruise-5314901",
      "source": "Channel News Asia",
      "region": "Global",
      "published": "2025-08-26T19:22:00+08:00",
      "sentiment": "positive"
    },
    {
      "title": "Wala Wala Cafe Bar reverses closure plan, remains in Holland Village",
      "url": "https://www.channelnewsasia.com/dining/wala-wala-holland-village-5314906",
      "source": "Channel News Asia",
      "region": "Global",
      "published": "2025-08-26T19:18:00+08:00",
      "sentiment": "neutral"
    },
    {
      "title": "As Pakistan battles monsoon floods, experts fear extreme weather will worsen with climate change",
      "url": "https://www.channelnewsasia.com/asia/pakistan-monsoon-flash-floods-cloudbursts-analysts-5314746",
      "source": "Channel News Asia",
      "region": "South America",
      "published": "2025-08-26T19:16:17+08:00",
      "sentiment": "negative"
    },
    {
      "title": "Exclusive-Stellantis shelves Level 3 driver-assistance program as it downscales software ambitions, sources say",
      "url": "https://www.channelnewsasia.com/business/exclusive-stellantis-shelves-level-3-driver-assistance-program-it-downscales-software-ambitions-sources-say-5314961",
      "source": "Channel News Asia",
      "region": "North America",
      "published": "2025-08-26T19:10:39+08:00",
      "sentiment": "neutral"
    },
    {
      "title": "Spotify announces messaging feature for free, premium users",
      "url": "https://www.channelnewsasia.com/business/spotify-announces-messaging-feature-free-premium-users-5314941",
      "source": "Channel News Asia",
      "region": "North America",
      "published": "2025-08-26T19:05:31+08:00",
      "sentiment": "positive"
    },
    {
      "title": "AT&T to buy spectrum licenses from EchoStar for about $23 billion",
      "url": "https://www.channelnewsasia.com/business/att-buy-spectrum-licenses-echostar-about-23-billion-5314896",
      "source": "Channel News Asia",
      "region": "Global",
      "published": "2025-08-26T18:43:20+08:00",
      "sentiment": "neutral"
    },
    {
      "title": "AT&T to buy some spectrum licenses from EchoStar for $23 billion",
      "url": "https://www.channelnewsasia.com/business/att-buy-some-spectrum-licenses-echostar-23-billion-5314896",
      "source": "Channel News Asia",
      "region": "Global",
      "published": "2025-08-26T18:43:20+08:00",
      "sentiment": "neutral"
    },
    {
      "title": "AT&T to buy wireless spectrum licenses from EchoStar for $23 billion",
      "url": "https://www.channelnewsasia.com/business/att-buy-wireless-spectrum-licenses-echostar-23-billion-5314896",
      "source": "Channel News Asia",
      "region": "Global",
      "published": "2025-08-26T18:43:20+08:00",
      "sentiment": "neutral"
    },
    {
      "title": "Godon joins Ineos on three-year contract",
      "url": "https://www.channelnewsasia.com/sport/godon-joins-ineos-three-year-contract-5314891",
      "source": "Channel News Asia",
      "region": "Global",
      "published": "2025-08-26T18:38:38+08:00",
      "sentiment": "neutral"
    },
    {
      "title": "Malaysia-S\u2019pore student exchange initiative will help plant seeds of trust, cooperation: Chan Chun Sing",
      "url": "https://www.straitstimes.com/singapore/malaysia-spore-student-exchange-initiative-will-help-plant-seeds-of-trust-cooperation-chan-chun-sing",
      "source": "Straits Times",
      "region": "North America",
      "published": "2025-08-26T18:37:18+08:00",
      "sentiment": "positive"
    },
    {
      "title": "Milo\u2019s limited-edition Breaktime Set plushies return to supermarkets with a new gem",
      "url": "https://www.straitstimes.com/singapore/milos-limited-edition-breaktime-set-plushies-return-to-supermarkets-with-a-new-gem",
      "source": "Straits Times",
      "region": "North America",
      "published": "2025-08-26T18:33:00+08:00",
      "sentiment": "neutral"
    },
    {
      "title": "Thomson Medical Group shares jump nearly 40% after US$4.3 billion Johor project launch",
      "url": "https://www.channelnewsasia.com/business/thomson-medical-group-share-price-jump-johor-bay-project-5314806",
      "source": "Channel News Asia",
      "region": "Asia-Pacific",
      "published": "2025-08-26T18:24:00+08:00",
      "sentiment": "positive"
    },
    {
      "title": "Johor quakes a reminder that severe tremors can impact Malaysia, Singapore",
      "url": "https://www.channelnewsasia.com/asia/malaysia-earthquake-tremors-johor-singapore-mersing-fault-zone-5314786",
      "source": "Channel News Asia",
      "region": "Asia-Pacific",
      "published": "2025-08-26T18:23:29+08:00",
      "sentiment": "negative"
    },
    {
      "title": "Modern Pentathlon-Pentathletes embracing obstacle course challenge at World Championships",
      "url": "https://www.channelnewsasia.com/sport/modern-pentathlon-pentathletes-embracing-obstacle-course-challenge-world-championships-5314866",
      "source": "Channel News Asia",
      "region": "Global",
      "published": "2025-08-26T18:11:03+08:00",
      "sentiment": "positive"
    },
    {
      "title": "Nvidia set for $260 billion price swing after earnings, options indicate",
      "url": "https://www.channelnewsasia.com/business/nvidia-set-260-billion-price-swing-after-earnings-options-indicate-5314836",
      "source": "Channel News Asia",
      "region": "Global",
      "published": "2025-08-26T18:01:08+08:00",
      "sentiment": "neutral"
    },
    {
      "title": "Apple Watch not a 'CO2-neutral product', German court finds",
      "url": "https://www.channelnewsasia.com/business/apple-watch-not-co2-neutral-product-german-court-finds-5314841",
      "source": "Channel News Asia",
      "region": "Global",
      "published": "2025-08-26T17:58:49+08:00",
      "sentiment": "neutral"
    },
    {
      "title": "Apple Watch not a 'CO2-neutral product,' German court finds",
      "url": "https://www.channelnewsasia.com/business/apple-watch-not-co2-neutral-product-german-court-finds-5314841",
      "source": "Channel News Asia",
      "region": "Global",
      "published": "2025-08-26T17:58:49+08:00",
      "sentiment": "neutral"
    },
    {
      "title": "Two arrested for peddling drugs in Bengaluru; \u20b941 lakh worth of ganja recovered",
      "url": "https://www.thehindu.com/news/national/karnataka/two-arrested-for-peddling-drugs-in-bengaluru-41-lakh-worth-of-ganja-recovered/article69978764.ece",
      "source": "The Hindu",
      "region": "Asia-Pacific",
      "published": "2025-08-26T17:52:00+05:30",
      "sentiment": "negative"
    },
    {
      "title": "US-Pakistan trade deal brings relief to exporters, but also pressure to innovate",
      "url": "https://www.channelnewsasia.com/world/pakistan-usa-trade-deal-tariff-export-business-innovate-5314616",
      "source": "Channel News Asia",
      "region": "North America",
      "published": "2025-08-26T17:46:47+08:00",
      "sentiment": "positive"
    },
    {
      "title": "Suspension of Vigilance Court employee over secret recordings sparks row",
      "url": "https://www.thehindu.com/news/national/kerala/suspension-of-vigilance-court-employee-over-secret-recordings-sparks-row/article69979029.ece",
      "source": "The Hindu",
      "region": "North America",
      "published": "2025-08-26T17:38:50+05:30",
      "sentiment": "positive"
    },
    {
      "title": "What to expect from the 63rd edition of the Bengaluru Ganesh Utsava in 2025",
      "url": "https://www.thehindu.com/news/cities/bangalore/what-to-expect-from-the-63rd-edition-of-the-bengaluru-ganesh-utsava-in-2025/article69963723.ece",
      "source": "The Hindu",
      "region": "North America",
      "published": "2025-08-26T17:38:09+05:30",
      "sentiment": "positive"
    },
    {
      "title": "19 major vape smuggling cases stopped at S\u2019pore checkpoints, 90,000 vapes seized from April to June",
      "url": "https://www.straitstimes.com/singapore/courts-crime/19-major-vape-smuggling-cases-stopped-at-spores-checkpoints-90000-vapes-seized-from-april-to-june",
      "source": "Straits Times",
      "region": "North America",
      "published": "2025-08-26T17:37:53+08:00",
      "sentiment": "negative"
    },
    {
      "title": "19 major vape smuggling cases stopped at S\u2019pore\u2019s checkpoints, 90,000 vapes seized from April to June",
      "url": "https://www.straitstimes.com/singapore/courts-crime/19-major-vape-smuggling-cases-stopped-at-spores-checkpoints-90000-vapes-seized-from-april-to-june",
      "source": "Straits Times",
      "region": "North America",
      "published": "2025-08-26T17:37:53+08:00",
      "sentiment": "negative"
    },
    {
      "title": "Husband held for dowry death in U.P.'s Ballia",
      "url": "https://www.thehindu.com/news/national/uttar-pradesh/husband-held-for-dowry-death-in-ups-ballia/article69979129.ece",
      "source": "The Hindu",
      "region": "North America",
      "published": "2025-08-26T17:36:21+05:30",
      "sentiment": "negative"
    },
    {
      "title": "Jarange firm on quota agitation in Mumbai from August 29; Government's attempt to dissuade him fails",
      "url": "https://www.thehindu.com/news/national/maharashtra/jarange-firm-on-quota-agitation-in-mumbai-from-august-29/article69979078.ece",
      "source": "The Hindu",
      "region": "North America",
      "published": "2025-08-26T17:32:18+05:30",
      "sentiment": "positive"
    },
    {
      "title": "'Is it time to pause H-1B?' asks US Senator: Ticking clock for Indian students",
      "url": "https://timesofindia.indiatimes.com/education/news/is-it-time-to-pause-h-1b-asks-us-senator-mike-lee-a-ticking-clock-for-indian-students-and-professionals/articleshow/123521887.cms",
      "source": "Times of India",
      "region": "Asia-Pacific",
      "published": "2025-08-26T17:30:00+05:30",
      "sentiment": "negative"
    },
    {
      "title": "HSBC failed to disclose banking relationship in more than 4200 research reports, Hong Kong authorities say",
      "url": "https://www.channelnewsasia.com/business/hsbc-failed-disclose-banking-relationship-more-4200-research-reports-hong-kong-authorities-say-5314741",
      "source": "Channel News Asia",
      "region": "Global",
      "published": "2025-08-26T17:26:06+08:00",
      "sentiment": "negative"
    },
    {
      "title": "HSBC fined $4.2 million by Hong Kong regulators over disclosure failure",
      "url": "https://www.channelnewsasia.com/business/hsbc-fined-42-million-hong-kong-regulators-over-disclosure-failure-5314741",
      "source": "Channel News Asia",
      "region": "Global",
      "published": "2025-08-26T17:26:06+08:00",
      "sentiment": "negative"
    },
    {
      "title": "Hong Kong fines HSBC over disclosure failures",
      "url": "https://www.channelnewsasia.com/business/hong-kong-fines-hsbc-disclosure-failures-investment-5314741",
      "source": "Channel News Asia",
      "region": "Global",
      "published": "2025-08-26T17:26:00+08:00",
      "sentiment": "negative"
    },
    {
      "title": "IndiGo, Air India Express add more flights for Kannur airport ahead of Onam",
      "url": "https://www.thehindu.com/news/national/kerala/indigo-air-india-express-add-more-flights-for-kannur-airport-ahead-of-onam/article69979038.ece",
      "source": "The Hindu",
      "region": "Asia-Pacific",
      "published": "2025-08-26T17:19:16+05:30",
      "sentiment": "neutral"
    },
    {
      "title": "Stunning prediction! Shreyas Iyer can captain India to a World Cup win'",
      "url": "https://timesofindia.indiatimes.com/sports/cricket/news/shreyas-iyer-can-captain-india-to-a-world-cup-win-stunning-prediction-on-iyer-after-asia-cup-snub/articleshow/123525465.cms",
      "source": "Times of India",
      "region": "Asia-Pacific",
      "published": "2025-08-26T17:13:59+05:30",
      "sentiment": "positive"
    },
    {
      "title": "Calcutta University, West Bengal government set for confrontation over exam date",
      "url": "https://www.thehindu.com/news/national/west-bengal/calcutta-university-west-bengal-government-set-for-confrontation-over-exam-date/article69978960.ece",
      "source": "The Hindu",
      "region": "North America",
      "published": "2025-08-26T17:12:23+05:30",
      "sentiment": "negative"
    },
    {
      "title": "Donald Trump gives \u2018reminder\u2019 to China while warning of more tariff",
      "url": "https://timesofindia.indiatimes.com/technology/tech-news/200-chinese-planes-were-unable-to-fly-because-us-did-not-give-donald-trump-reminder-to-china-while-warning-of-more-tariff/articleshow/123525416.cms",
      "source": "Times of India",
      "region": "Asia-Pacific",
      "published": "2025-08-26T17:11:04+05:30",
      "sentiment": "negative"
    },
    {
      "title": "Two police officers killed in eastern Australia shooting",
      "url": "https://www.channelnewsasia.com/world/two-police-officers-killed-eastern-australia-shooting-victoria-5314711",
      "source": "Channel News Asia",
      "region": "North America",
      "published": "2025-08-26T17:06:37+08:00",
      "sentiment": "negative"
    },
    {
      "title": "India growth likely slowed to 6.7% in April\u2013June and set to ease further: Reuters poll",
      "url": "https://www.channelnewsasia.com/business/india-growth-likely-slowed-67-april-june-and-set-ease-further-reuters-poll-5314721",
      "source": "Channel News Asia",
      "region": "Asia-Pacific",
      "published": "2025-08-26T17:05:17+08:00",
      "sentiment": "positive"
    },
    {
      "title": "India growth likely slowed to 6.7% in April\u2013June and set to ease further",
      "url": "https://www.channelnewsasia.com/business/india-growth-likely-slowed-67-april-june-and-set-ease-further-5314721",
      "source": "Channel News Asia",
      "region": "Asia-Pacific",
      "published": "2025-08-26T17:05:17+08:00",
      "sentiment": "positive"
    },
    {
      "title": "Cheteshwar Pujara retires: How much pension will he earn each month?",
      "url": "https://timesofindia.indiatimes.com/sports/cricket/news/cheteshwar-pujara-retires-how-much-pension-will-he-earn-each-month/articleshow/123524630.cms",
      "source": "Times of India",
      "region": "Asia-Pacific",
      "published": "2025-08-26T17:05:01+05:30",
      "sentiment": "positive"
    },
    {
      "title": "CID arrests prime accused in Shivaprakash murder case in Delhi airport",
      "url": "https://www.thehindu.com/news/national/karnataka/cid-arrests-prime-accused-in-shivaprakash-murder-case-in-delhi-airport-bengaluru/article69978812.ece",
      "source": "The Hindu",
      "region": "North America",
      "published": "2025-08-26T16:51:15+05:30",
      "sentiment": "negative"
    },
    {
      "title": "Actor Tay Ping Hui cautions fans after fake AI video of him promoting 'medication' makes rounds online",
      "url": "https://www.channelnewsasia.com/entertainment/tay-ping-hui-ai-scam-warns-fans-5314676",
      "source": "Channel News Asia",
      "region": "Global",
      "published": "2025-08-26T16:51:13+08:00",
      "sentiment": "negative"
    },
    {
      "title": "Akasa Air to fly daily from Bengaluru to Phuket from October 1",
      "url": "https://www.thehindu.com/news/national/akasa-air-to-fly-daily-from-bengaluru-to-phuket-from-october-1/article69978919.ece",
      "source": "The Hindu",
      "region": "Europe",
      "published": "2025-08-26T16:47:36+05:30",
      "sentiment": "neutral"
    },
    {
      "title": "Police arrest chain snatcher, recover \u20b923.5 lakh worth gold ornaments",
      "url": "https://www.thehindu.com/news/national/telangana/police-arrest-chain-snatcher-recover-235-lakh-worth-gold-ornaments/article69978614.ece",
      "source": "The Hindu",
      "region": "Asia-Pacific",
      "published": "2025-08-26T16:43:38+05:30",
      "sentiment": "negative"
    },
    {
      "title": "'Blood Moon' total lunar eclipse to happen over Singapore's sky on Sep 7",
      "url": "https://www.channelnewsasia.com/singapore/blood-moon-total-lunar-eclipse-singapore-sep-7-astronomy-night-sky-5314546",
      "source": "Channel News Asia",
      "region": "Asia-Pacific",
      "published": "2025-08-26T16:41:00+08:00",
      "sentiment": "neutral"
    },
    {
      "title": "India to probe giant zoo run by son of Asia's richest person",
      "url": "https://www.channelnewsasia.com/asia/india-probe-zoo-vantara-anant-ambani-illegal-imports-financial-misconduct-5314651",
      "source": "Channel News Asia",
      "region": "Asia-Pacific",
      "published": "2025-08-26T16:40:00+08:00",
      "sentiment": "positive"
    },
    {
      "title": "One ball, two sixes, 13 runs! Sanju Samson does the unthinkable ahead of Asia Cup - Watch",
      "url": "https://timesofindia.indiatimes.com/sports/cricket/news/one-ball-two-sixes-13-runs-sanju-samson-does-the-unthinkable-ahead-of-asia-cup-watch/articleshow/123524149.cms",
      "source": "Times of India",
      "region": "Asia-Pacific",
      "published": "2025-08-26T16:34:28+05:30",
      "sentiment": "positive"
    },
    {
      "title": "Towering wall of dust rolls through US city, leaving thousands without power",
      "url": "https://www.channelnewsasia.com/world/dust-storm-haboob-rolls-through-phoenix-arizona-extreme-weather-monsoon-5314161",
      "source": "Channel News Asia",
      "region": "North America",
      "published": "2025-08-26T16:22:21+08:00",
      "sentiment": "neutral"
    },
    {
      "title": "Akhilesh meets Opposition V-P pick Sudershan Reddy, terms September 9 polls 'fight for justice'",
      "url": "https://www.thehindu.com/news/national/uttar-pradesh/akhilesh-meets-opposition-v-p-pick-sudershan-reddy-terms-september-9-polls-fight-for-justice/article69978856.ece",
      "source": "The Hindu",
      "region": "North America",
      "published": "2025-08-26T16:19:59+05:30",
      "sentiment": "positive"
    },
    {
      "title": "Mass evacuations in eastern Pakistan as India releases water from swollen rivers",
      "url": "https://www.channelnewsasia.com/asia/mass-evacuation-eastern-pakistan-india-release-water-swollen-river-5314556",
      "source": "Channel News Asia",
      "region": "Asia-Pacific",
      "published": "2025-08-26T16:19:00+08:00",
      "sentiment": "neutral"
    },
    {
      "title": "Israeli protesters call for hostage deal ahead of Cabinet meeting",
      "url": "https://www.channelnewsasia.com/world/israel-protest-call-hostage-deal-tel-aviv-5314606",
      "source": "Channel News Asia",
      "region": "Middle East",
      "published": "2025-08-26T16:17:00+08:00",
      "sentiment": "negative"
    },
    {
      "title": "Landslide hits Mata Vaishno Devi shrine route in J&K's Reasi district",
      "url": "https://timesofindia.indiatimes.com/india/landslide-hits-mata-vaishno-devi-shrine-route-in-jks-reasi-district/articleshow/123524110.cms",
      "source": "Times of India",
      "region": "Asia-Pacific",
      "published": "2025-08-26T16:15:44+05:30",
      "sentiment": "neutral"
    },
    {
      "title": "J&K rains: Landslide hits Mata Vaishno Devi shrine route; yatra suspended",
      "url": "https://timesofindia.indiatimes.com/india/landslide-hits-mata-vaishno-devi-shrine-route-in-jks-reasi-district/articleshow/123524110.cms",
      "source": "Times of India",
      "region": "North America",
      "published": "2025-08-26T16:15:44+05:30",
      "sentiment": "negative"
    },
    {
      "title": "Telangana CM Revanth Reddy joins Rahul Gandhi\u2019s Yatra in Bihar",
      "url": "https://www.thehindu.com/news/national/telangana/telangana-cm-revanth-reddy-joins-rahul-gandhis-yatra-in-bihar/article69978783.ece",
      "source": "The Hindu",
      "region": "Asia-Pacific",
      "published": "2025-08-26T16:09:23+05:30",
      "sentiment": "neutral"
    },
    {
      "title": "Two get life imprisonment for raping minor",
      "url": "https://www.thehindu.com/news/national/andhra-pradesh/two-get-life-imprisonment-for-raping-minor/article69978369.ece",
      "source": "The Hindu",
      "region": "Asia-Pacific",
      "published": "2025-08-26T16:05:45+05:30",
      "sentiment": "negative"
    },
    {
      "title": "'Didn't expect him to call us thieves': Mamata hits back at PM Modi",
      "url": "https://timesofindia.indiatimes.com/india/didnt-expect-him-to-call-us-thieves-mamata-banerjee-hits-back-accuses-pm-modi-of-turning-blind-eye-to-corruption-under-double-engine-governments/articleshow/123523457.cms",
      "source": "Times of India",
      "region": "North America",
      "published": "2025-08-26T16:04:15+05:30",
      "sentiment": "negative"
    },
    {
      "title": "Atham pageantry heralds Onam in Kerala with artistic fervour, social messages",
      "url": "https://www.thehindu.com/news/national/kerala/atham-pageantry-heralds-onam-in-kerala-with-artistic-fervour-social-messages/article69978716.ece",
      "source": "The Hindu",
      "region": "Asia-Pacific",
      "published": "2025-08-26T16:04:01+05:30",
      "sentiment": "positive"
    },
    {
      "title": "After blasting Gambhir, ex-India player slams Dhoni - 'He did not like me'",
      "url": "https://timesofindia.indiatimes.com/sports/cricket/news/after-blasting-gautam-gambhir-ex-india-player-accuses-ms-dhoni-of-favouritism-he-did-not-like-me/articleshow/123523863.cms",
      "source": "Times of India",
      "region": "North America",
      "published": "2025-08-26T16:03:57+05:30",
      "sentiment": "negative"
    },
    {
      "title": "Sarfaraz Khan on fire! Sends strong message to selectors ahead of Windies Tests",
      "url": "https://timesofindia.indiatimes.com/sports/cricket/news/sarfaraz-khan-on-fire-back-to-back-tons-send-strong-message-to-selectors-ahead-of-windies-tests/articleshow/123523814.cms",
      "source": "Times of India",
      "region": "Asia-Pacific",
      "published": "2025-08-26T15:59:06+05:30",
      "sentiment": "negative"
    },
    {
      "title": "Deputy CM D.K. Shivakumar inspects pothole filling work in Bengaluru, urges citizens to report on \u2018gundi gamana\u2019 app",
      "url": "https://www.thehindu.com/news/national/karnataka/deputy-cm-dk-shivakumar-inspects-pothole-filling-work-in-bengaluru-urges-citizens-to-report-on-gundi-gamana-app/article69978407.ece",
      "source": "The Hindu",
      "region": "Asia-Pacific",
      "published": "2025-08-26T15:58:24+05:30",
      "sentiment": "neutral"
    },
    {
      "title": "INS Udaygiri and INS Himgiri commissioned by Union Defence Minister Rajnath Singh at Visakhapatnam",
      "url": "https://www.thehindu.com/news/national/ins-udaygiri-and-ins-himgiri-commissioned-by-union-defence-minister-rajnath-singh-at-visakhapatnam/article69978776.ece",
      "source": "The Hindu",
      "region": "Asia-Pacific",
      "published": "2025-08-26T15:57:40+05:30",
      "sentiment": "positive"
    },
    {
      "title": "Rain fury in J&K: Roads washed away, flood alerts issued; 10 videos show havoc",
      "url": "https://timesofindia.indiatimes.com/india/rain-fury-in-jk-roads-washed-away-flood-alerts-sounded-8-scary-videos-that-show-devastation/articleshow/123523632.cms",
      "source": "Times of India",
      "region": "Asia-Pacific",
      "published": "2025-08-26T15:55:23+05:30",
      "sentiment": "negative"
    },
    {
      "title": "The best action camera in Singapore for travel, vlogging and sports",
      "url": "https://www.channelnewsasia.com/buyers-guide/best-action-camera-5314426",
      "source": "Channel News Asia",
      "region": "Asia-Pacific",
      "published": "2025-08-26T15:52:44+08:00",
      "sentiment": "positive"
    },
    {
      "title": "Nasi lemak hawker goes viral after old photos of her as an SQ calendar girl surface",
      "url": "https://www.channelnewsasia.com/dining/aliff-nasi-lemak-former-sq-calendar-girl-singapore-airlines-5314531",
      "source": "Channel News Asia",
      "region": "North America",
      "published": "2025-08-26T15:52:13+08:00",
      "sentiment": "negative"
    },
    {
      "title": "Alcaraz amused by reaction to his accidental buzz cut",
      "url": "https://www.channelnewsasia.com/sport/alcaraz-amused-reaction-his-accidental-buzz-cut-5314596",
      "source": "Channel News Asia",
      "region": "North America",
      "published": "2025-08-26T15:48:16+08:00",
      "sentiment": "positive"
    },
    {
      "title": "Government school window lintel collapses, 3 students injured at Devanahalli near Bengaluru, complaint against Bharat Electronics Limited (BEL)",
      "url": "https://www.thehindu.com/news/national/karnataka/government-school-window-lintel-collapses-3-students-injured-at-devanahalli-near-bengaluru-complaint-against-bharat-electronics-limited-bel/article69978648.ece",
      "source": "The Hindu",
      "region": "Asia-Pacific",
      "published": "2025-08-26T15:48:04+05:30",
      "sentiment": "negative"
    },
    {
      "title": "Three students injured as government school window lintel collapses at Devanahalli near Bengaluru, plaint against Bharat Electronics Limited",
      "url": "https://www.thehindu.com/news/cities/bangalore/government-school-window-lintel-collapses-3-students-injured-at-devanahalli-near-bengaluru-complaint-against-bharat-electronics-limited-bel/article69978648.ece",
      "source": "The Hindu",
      "region": "Asia-Pacific",
      "published": "2025-08-26T15:48:04+05:30",
      "sentiment": "negative"
    },
    {
      "title": "Record! 102-year-old, with heart condition, becomes oldest to climb Mount Fuji",
      "url": "https://timesofindia.indiatimes.com/sports/more-sports/others/japans-102-year-old-with-heart-condition-becomes-oldest-to-climb-mount-fuji/articleshow/123523410.cms",
      "source": "Times of India",
      "region": "Asia-Pacific",
      "published": "2025-08-26T15:47:47+05:30",
      "sentiment": "positive"
    },
    {
      "title": "Three buildings in dilapidated state to be demolished in Srisailam",
      "url": "https://www.thehindu.com/news/national/andhra-pradesh/three-buildings-in-dilapidated-state-to-be-demolished-in-srisailam/article69978063.ece",
      "source": "The Hindu",
      "region": "Asia-Pacific",
      "published": "2025-08-26T15:47:44+05:30",
      "sentiment": "neutral"
    },
    {
      "title": "Expansion of breakfast scheme futile without serving quality food, says Nainar Nagenthran",
      "url": "https://www.thehindu.com/news/national/tamil-nadu/expansion-of-breakfast-scheme-futile-without-serving-quality-food-says-nainar-nagenthran/article69978680.ece",
      "source": "The Hindu",
      "region": "Asia-Pacific",
      "published": "2025-08-26T15:44:42+05:30",
      "sentiment": "negative"
    },
    {
      "title": "Purificatory ritual at TTD temples in Kadapa district",
      "url": "https://www.thehindu.com/news/national/andhra-pradesh/purificatory-ritual-at-ttd-temples-in-kadapa-district/article69978162.ece",
      "source": "The Hindu",
      "region": "Asia-Pacific",
      "published": "2025-08-26T15:44:01+05:30",
      "sentiment": "neutral"
    },
    {
      "title": "Kannur jail smuggling racket: Youth admits to throwing ganja, mobiles inside for cash",
      "url": "https://www.thehindu.com/news/national/kerala/kannur-jail-smuggling-racket-youth-admits-to-throwing-ganja-mobiles-inside-for-cash/article69978701.ece",
      "source": "The Hindu",
      "region": "North America",
      "published": "2025-08-26T15:43:13+05:30",
      "sentiment": "negative"
    },
    {
      "title": "Klarna to seek valuation of up to $14 billion in IPO next month, sources say",
      "url": "https://www.channelnewsasia.com/business/klarna-seek-valuation-up-14-billion-ipo-next-month-sources-say-5314586",
      "source": "Channel News Asia",
      "region": "Global",
      "published": "2025-08-26T15:42:37+08:00",
      "sentiment": "neutral"
    },
    {
      "title": "Fake NRI admissions racket in medical education: The new red lines",
      "url": "https://timesofindia.indiatimes.com/education/news/fake-nri-admissions-racket-in-medical-education-the-new-red-lines-on-who-is-and-who-isnt-a-guardian/articleshow/123523443.cms",
      "source": "Times of India",
      "region": "North America",
      "published": "2025-08-26T15:41:08+05:30",
      "sentiment": "negative"
    },
    {
      "title": "Indian Navy milestone: Rajnath commissions stealth frigates INS Udaygiri and Himgiri",
      "url": "https://timesofindia.indiatimes.com/india/maritime-milestone-indian-navy-commissions-twin-stealth-frigates-ins-udaygiri-and-himgiri-why-is-it-important/articleshow/123522962.cms",
      "source": "Times of India",
      "region": "Asia-Pacific",
      "published": "2025-08-26T15:37:24+05:30",
      "sentiment": "positive"
    },
    {
      "title": "Second round of CET-NEET counselling delayed: KEA to request extension of deadline for engineering admission in Karnataka",
      "url": "https://www.thehindu.com/news/national/karnataka/second-round-of-cet-neet-counselling-delayed-kea-to-request-extension-of-deadline-for-engineering-admission-in-karnataka/article69978542.ece",
      "source": "The Hindu",
      "region": "Asia-Pacific",
      "published": "2025-08-26T15:37:07+05:30",
      "sentiment": "negative"
    },
    {
      "title": "A.P. is one of the few States that introduced sector-specific industrial policies: MSME Minister",
      "url": "https://www.thehindu.com/news/national/andhra-pradesh/ap-is-one-of-the-few-states-that-introduced-sector-specific-industrial-policies-msme-minister/article69977757.ece",
      "source": "The Hindu",
      "region": "North America",
      "published": "2025-08-26T15:35:02+05:30",
      "sentiment": "positive"
    },
    {
      "title": "Telangana HRC summons authorities of Hyderabad colleges which withheld students\u2019 certificates",
      "url": "https://www.thehindu.com/news/national/telangana/telangana-hrc-summons-authorities-of-hyderabad-colleges-which-withheld-students-certificates/article69975810.ece",
      "source": "The Hindu",
      "region": "Asia-Pacific",
      "published": "2025-08-26T15:31:43+05:30",
      "sentiment": "neutral"
    },
    {
      "title": "Never expected PM Modi to call us \u2018thieves\u2019, he should respect my chair as I do his, says Mamata Banerjee",
      "url": "https://www.thehindu.com/news/national/west-bengal/never-expected-pm-modi-to-call-us-thieves-he-should-respect-my-chair-as-i-do-his-says-mamata-banerjee/article69978682.ece",
      "source": "The Hindu",
      "region": "North America",
      "published": "2025-08-26T15:31:02+05:30",
      "sentiment": "positive"
    },
    {
      "title": "Foodcourt staff in S\u2019pore trained to spot diners who may be abused by a loved one",
      "url": "https://www.straitstimes.com/singapore/community/food-court-staff-in-spore-trained-to-spot-diners-who-may-be-abused-by-a-loved-one",
      "source": "Straits Times",
      "region": "North America",
      "published": "2025-08-26T15:30:00+08:00",
      "sentiment": "positive"
    },
    {
      "title": "Malaysia's commodities ministry seeks tax exemption for palm oil raw materials",
      "url": "https://www.channelnewsasia.com/business/malaysias-commodities-ministry-seeks-tax-exemption-palm-oil-raw-materials-5314566",
      "source": "Channel News Asia",
      "region": "Asia-Pacific",
      "published": "2025-08-26T15:29:09+08:00",
      "sentiment": "neutral"
    },
    {
      "title": "China's Xi Jingping to welcome Vladimir Putin, PM Modi in grand show of solidarity",
      "url": "https://www.thehindu.com/news/international/chinas-xi-jingping-to-welcome-vladimir-putin-pm-modi-in-grand-show-of-solidarity/article69978606.ece",
      "source": "The Hindu",
      "region": "Asia-Pacific",
      "published": "2025-08-26T15:27:30+05:30",
      "sentiment": "positive"
    },
    {
      "title": "China's Xi Jinping to welcome Vladimir Putin, PM Modi in grand show of solidarity",
      "url": "https://www.thehindu.com/news/international/chinas-xi-jingping-to-welcome-vladimir-putin-pm-modi-in-grand-show-of-solidarity/article69978606.ece",
      "source": "The Hindu",
      "region": "Asia-Pacific",
      "published": "2025-08-26T15:27:30+05:30",
      "sentiment": "positive"
    },
    {
      "title": "Former APCID chief and Fire Services D-G N. Sanjay surrenders in ACB Court, remanded",
      "url": "https://www.thehindu.com/news/national/andhra-pradesh/former-apcid-chief-and-fire-services-d-g-n-sanjay-surrenders-in-acb-court-remanded/article69978553.ece",
      "source": "The Hindu",
      "region": "Asia-Pacific",
      "published": "2025-08-26T15:26:51+05:30",
      "sentiment": "positive"
    },
    {
      "title": "Bengaluru Metro security guard\u2019s fall on tracks sparks concerns about long working hours and lack of safety barriers",
      "url": "https://www.thehindu.com/news/cities/bangalore/namma-metro-security-guards-fall-on-tracks-sparks-concerns-in-bengaluru-about-long-working-hours-and-lack-of-safety-barriers/article69978500.ece",
      "source": "The Hindu",
      "region": "North America",
      "published": "2025-08-26T15:25:40+05:30",
      "sentiment": "negative"
    },
    {
      "title": "'I don't want to be defense only': Trump's new 'department of war' idea",
      "url": "https://timesofindia.indiatimes.com/world/us/i-dont-want-to-be-defense-only-trumps-new-department-of-war-idea-what-is-it/articleshow/123522767.cms",
      "source": "Times of India",
      "region": "North America",
      "published": "2025-08-26T15:23:01+05:30",
      "sentiment": "negative"
    },
    {
      "title": "Wood can help New Zealand break new ground at World Cup, says coach Bazeley",
      "url": "https://www.channelnewsasia.com/sport/wood-can-help-new-zealand-break-new-ground-world-cup-says-coach-bazeley-5314536",
      "source": "Channel News Asia",
      "region": "Global",
      "published": "2025-08-26T15:17:49+08:00",
      "sentiment": "positive"
    },
    {
      "title": "Six registered political parties receive show-cause notices from Chennai district election office",
      "url": "https://www.thehindu.com/news/cities/chennai/six-registered-political-parties-receive-show-cause-notices-from-chennai-district-election-office/article69975839.ece",
      "source": "The Hindu",
      "region": "Asia-Pacific",
      "published": "2025-08-26T15:08:44+05:30",
      "sentiment": "positive"
    },
    {
      "title": "Three held for assaulting labourer for wearing saffron towel at Kalasipalya in Bengaluru",
      "url": "https://www.thehindu.com/news/national/karnataka/three-held-for-assaulting-labourer-for-wearing-saffron-towel-at-kalasipalya-in-bengaluru/article69978279.ece",
      "source": "The Hindu",
      "region": "North America",
      "published": "2025-08-26T15:08:13+05:30",
      "sentiment": "negative"
    },
    {
      "title": "Traffic suspended on Jammu-Srinagar National Highway amid rains across Jammu",
      "url": "https://www.thehindu.com/news/national/jammu-and-kashmir/traffic-suspended-on-jammu-srinagar-national-highway-amid-rains-across-jammu/article69978584.ece",
      "source": "The Hindu",
      "region": "North America",
      "published": "2025-08-26T15:01:56+05:30",
      "sentiment": "negative"
    }
  ]
}