{
  "generated_at": "2025-08-29T08:51:18.049697+00:00",
  "window_hours": 24,
  "totals": {
    "positive": 1315,
    "neutral": 419,
    "negative": 1518
  },
  "by_publication": [
    {
      "source": "Independent",
      "positive": 221,
      "neutral": 87,
      "negative": 295,
      "count": 603,
      "region": "North America"
    },
    {
      "source": "The Hindu",
      "positive": 125,
      "neutral": 66,
      "negative": 108,
      "count": 299,
      "region": "North America"
    },
    {
      "source": "Bloomberg",
      "positive": 118,
      "neutral": 21,
      "negative": 56,
      "count": 195,
      "region": "Europe"
    },
    {
      "source": "Channel News Asia",
      "positive": 61,
      "neutral": 42,
      "negative": 52,
      "count": 155,
      "region": "Africa"
    },
    {
      "source": "CBS News",
      "positive": 38,
      "neutral": 15,
      "negative": 86,
      "count": 139,
      "region": "North America"
    },
    {
      "source": "Times of India",
      "positive": 59,
      "neutral": 10,
      "negative": 60,
      "count": 129,
      "region": "North America"
    },
    {
      "source": "Fox News",
      "positive": 41,
      "neutral": 10,
      "negative": 77,
      "count": 128,
      "region": "North America"
    },
    {
      "source": "The Guardian",
      "positive": 27,
      "neutral": 3,
      "negative": 97,
      "count": 127,
      "region": "North America"
    },
    {
      "source": "Australian Broadcasting Corporation",
      "positive": 45,
      "neutral": 13,
      "negative": 62,
      "count": 120,
      "region": "Asia-Pacific"
    },
    {
      "source": "BBC Sport",
      "positive": 69,
      "neutral": 11,
      "negative": 22,
      "count": 102,
      "region": "Europe"
    },
    {
      "source": "BBC News",
      "positive": 33,
      "neutral": 17,
      "negative": 50,
      "count": 100,
      "region": "Europe"
    },
    {
      "source": "NBC News",
      "positive": 26,
      "neutral": 7,
      "negative": 55,
      "count": 88,
      "region": "North America"
    },
    {
      "source": "South China Morning Post",
      "positive": 41,
      "neutral": 0,
      "negative": 36,
      "count": 77,
      "region": "North America"
    },
    {
      "source": "Al Jazeera English",
      "positive": 18,
      "neutral": 5,
      "negative": 53,
      "count": 76,
      "region": "North America"
    },
    {
      "source": "Sky Sports",
      "positive": 37,
      "neutral": 17,
      "negative": 18,
      "count": 72,
      "region": "Europe"
    },
    {
      "source": "France 24",
      "positive": 28,
      "neutral": 3,
      "negative": 35,
      "count": 66,
      "region": "Europe"
    },
    {
      "source": "Euronews",
      "positive": 24,
      "neutral": 6,
      "negative": 34,
      "count": 64,
      "region": "Europe"
    },
    {
      "source": "CNBC",
      "positive": 31,
      "neutral": 5,
      "negative": 27,
      "count": 63,
      "region": "North America"
    },
    {
      "source": "Mashable",
      "positive": 34,
      "neutral": 11,
      "negative": 14,
      "count": 59,
      "region": "Global"
    },
    {
      "source": "Middle East Eye",
      "positive": 12,
      "neutral": 1,
      "negative": 40,
      "count": 53,
      "region": "Middle East"
    },
    {
      "source": "ESPN",
      "positive": 33,
      "neutral": 5,
      "negative": 15,
      "count": 53,
      "region": "North America"
    },
    {
      "source": "MarketWatch",
      "positive": 19,
      "neutral": 4,
      "negative": 21,
      "count": 44,
      "region": "North America"
    },
    {
      "source": "Irish Times",
      "positive": 10,
      "neutral": 6,
      "negative": 24,
      "count": 40,
      "region": "Global"
    },
    {
      "source": "Times of Israel",
      "positive": 13,
      "neutral": 4,
      "negative": 22,
      "count": 39,
      "region": "Middle East"
    },
    {
      "source": "AllAfrica",
      "positive": 18,
      "neutral": 6,
      "negative": 13,
      "count": 37,
      "region": "North America"
    },
    {
      "source": "Deutsche Welle",
      "positive": 11,
      "neutral": 3,
      "negative": 20,
      "count": 34,
      "region": "Asia-Pacific"
    },
    {
      "source": "NPR",
      "positive": 9,
      "neutral": 5,
      "negative": 17,
      "count": 31,
      "region": "North America"
    },
    {
      "source": "Financial Times",
      "positive": 9,
      "neutral": 4,
      "negative": 16,
      "count": 29,
      "region": "Europe"
    },
    {
      "source": "The Verge",
      "positive": 19,
      "neutral": 2,
      "negative": 6,
      "count": 27,
      "region": "Europe"
    },
    {
      "source": "New York Times",
      "positive": 5,
      "neutral": 4,
      "negative": 17,
      "count": 26,
      "region": "Europe"
    },
    {
      "source": "Engadget",
      "positive": 25,
      "neutral": 1,
      "negative": 0,
      "count": 26,
      "region": "North America"
    },
    {
      "source": "RT News",
      "positive": 8,
      "neutral": 6,
      "negative": 11,
      "count": 25,
      "region": "Europe"
    },
    {
      "source": "Straits Times",
      "positive": 6,
      "neutral": 8,
      "negative": 10,
      "count": 24,
      "region": "Asia-Pacific"
    },
    {
      "source": "ABC News",
      "positive": 7,
      "neutral": 0,
      "negative": 15,
      "count": 22,
      "region": "North America"
    },
    {
      "source": "Wired",
      "positive": 16,
      "neutral": 2,
      "negative": 2,
      "count": 20,
      "region": "North America"
    },
    {
      "source": "Sky News",
      "positive": 3,
      "neutral": 0,
      "negative": 13,
      "count": 16,
      "region": "North America"
    },
    {
      "source": "Ars Technica",
      "positive": 3,
      "neutral": 5,
      "negative": 4,
      "count": 12,
      "region": "North America"
    },
    {
      "source": "Sputnik News",
      "positive": 3,
      "neutral": 2,
      "negative": 6,
      "count": 11,
      "region": "North America"
    },
    {
      "source": "Washington Post",
      "positive": 2,
      "neutral": 0,
      "negative": 6,
      "count": 8,
      "region": "Europe"
    },
    {
      "source": "Telegraph",
      "positive": 4,
      "neutral": 2,
      "negative": 1,
      "count": 7,
      "region": "Europe"
    },
    {
      "source": "Buenos Aires Herald",
      "positive": 3,
      "neutral": 0,
      "negative": 2,
      "count": 5,
      "region": "South America"
    },
    {
      "source": "Daily News Egypt",
      "positive": 1,
      "neutral": 0,
      "negative": 0,
      "count": 1,
      "region": "North America"
    }
  ],
  "by_region": [
    {
      "region": "North America",
      "positive": 532,
      "neutral": 143,
      "negative": 682,
      "count": 1357
    },
    {
      "region": "Europe",
      "positive": 346,
      "neutral": 114,
      "negative": 347,
      "count": 807
    },
    {
      "region": "Asia-Pacific",
      "positive": 250,
      "neutral": 89,
      "negative": 239,
      "count": 578
    },
    {
      "region": "Global",
      "positive": 114,
      "neutral": 50,
      "negative": 83,
      "count": 247
    },
    {
      "region": "Middle East",
      "positive": 45,
      "neutral": 14,
      "negative": 135,
      "count": 194
    },
    {
      "region": "Africa",
      "positive": 18,
      "neutral": 7,
      "negative": 16,
      "count": 41
    },
    {
      "region": "South America",
      "positive": 10,
      "neutral": 2,
      "negative": 16,
      "count": 28
    }
  ],
  "by_topic": [
    {
      "topic": "Tech",
      "positive": 321,
      "neutral": 98,
      "negative": 381,
      "count": 800
    },
    {
      "topic": "Other",
      "positive": 211,
      "neutral": 95,
      "negative": 239,
      "count": 545
    },
    {
      "topic": "Politics",
      "positive": 187,
      "neutral": 56,
      "negative": 273,
      "count": 516
    },
    {
      "topic": "World",
      "positive": 134,
      "neutral": 38,
      "negative": 277,
      "count": 449
    },
    {
      "topic": "Sports",
      "positive": 183,
      "neutral": 43,
      "negative": 58,
      "count": 284
    },
    {
      "topic": "Business",
      "positive": 145,
      "neutral": 37,
      "negative": 64,
      "count": 246
    },
    {
      "topic": "Entertainment",
      "positive": 47,
      "neutral": 21,
      "negative": 55,
      "count": 123
    },
    {
      "topic": "Health",
      "positive": 27,
      "neutral": 12,
      "negative": 80,
      "count": 119
    },
    {
      "topic": "Regional",
      "positive": 19,
      "neutral": 8,
      "negative": 43,
      "count": 70
    },
    {
      "topic": "Local",
      "positive": 23,
      "neutral": 6,
      "negative": 28,
      "count": 57
    },
    {
      "topic": "Science",
      "positive": 18,
      "neutral": 5,
      "negative": 20,
      "count": 43
    }
  ],
  "sample_headlines": [
    {
      "title": "Singapore\u2019s Loh Kean Yew\u00a0stunned by world number 50 in quarter-finals,\u00a0exits BWF World Championships",
      "url": "https://www.channelnewsasia.com/sport/bwf-world-championships-badminton-team-singapore-loh-kean-yew-victor-lai-5321956",
      "source": "Channel News Asia",
      "region": "Asia-Pacific",
      "published": "2025-08-29T16:42:00+08:00",
      "sentiment": "positive"
    },
    {
      "title": "Japan should debate cap for foreign residents, government report says",
      "url": "https://www.channelnewsasia.com/east-asia/japan-foreign-residents-cap-debate-policy-5321921",
      "source": "Channel News Asia",
      "region": "Asia-Pacific",
      "published": "2025-08-29T16:26:00+08:00",
      "sentiment": "neutral"
    },
    {
      "title": "Marvell sinks as weak data center outlook stokes AI chip worries",
      "url": "https://www.channelnewsasia.com/business/marvell-sinks-weak-data-center-outlook-stokes-ai-chip-worries-5322041",
      "source": "Channel News Asia",
      "region": "Global",
      "published": "2025-08-29T16:21:55+08:00",
      "sentiment": "negative"
    },
    {
      "title": "NDP 2025 celebrated Singapore\u2019s diversity, vibrancy and inclusivity: President Tharman",
      "url": "https://www.straitstimes.com/singapore/ndp-2025-celebrated-singapores-diversity-vibrancy-and-inclusivity-president-tharman",
      "source": "Straits Times",
      "region": "Asia-Pacific",
      "published": "2025-08-29T16:15:00+08:00",
      "sentiment": "positive"
    },
    {
      "title": "Fenerbahce part ways with Mourinho",
      "url": "https://www.channelnewsasia.com/sport/fenerbahce-part-ways-mourinho-5322016",
      "source": "Channel News Asia",
      "region": "Global",
      "published": "2025-08-29T16:12:12+08:00",
      "sentiment": "neutral"
    },
    {
      "title": "Motorcyclist taken to hospital after accident with car on AYE",
      "url": "https://www.straitstimes.com/singapore/motorcyclist-taken-to-hospital-after-accident-with-car-on-aye",
      "source": "Straits Times",
      "region": "North America",
      "published": "2025-08-29T16:12:00+08:00",
      "sentiment": "negative"
    },
    {
      "title": "Eric Trump says Trump family 'loves' Bitcoin community, predicts $1 million valuation",
      "url": "https://www.channelnewsasia.com/business/eric-trump-says-trump-family-loves-bitcoin-community-predicts-1-million-valuation-5322001",
      "source": "Channel News Asia",
      "region": "Global",
      "published": "2025-08-29T16:03:22+08:00",
      "sentiment": "positive"
    },
    {
      "title": "No charges filed over Chua Chu Kang walkabout incident, PSP \u2018disappointed\u2019 over lack of explanation on outcome",
      "url": "https://www.straitstimes.com/singapore/politics/no-charges-filed-over-chua-chu-kang-walkabout-incident-psp-disappointed-over-lack-of-explanation-on",
      "source": "Straits Times",
      "region": "Global",
      "published": "2025-08-29T16:03:18+08:00",
      "sentiment": "positive"
    },
    {
      "title": "Eligible S\u2019poreans, PRs can get subsidised rates for shingles and pneumococcal vaccines from Sept 1",
      "url": "https://www.straitstimes.com/singapore/eligible-sporeans-prs-can-get-subsidised-rates-for-shingles-and-pneumococcal-vaccines-from-sept-1",
      "source": "Straits Times",
      "region": "Global",
      "published": "2025-08-29T15:40:01+08:00",
      "sentiment": "neutral"
    },
    {
      "title": "Japan seeks record defence budget, to triple drone spending",
      "url": "https://www.channelnewsasia.com/east-asia/japan-seeks-record-defence-budget-triple-drone-spending-5321916",
      "source": "Channel News Asia",
      "region": "Asia-Pacific",
      "published": "2025-08-29T15:24:00+08:00",
      "sentiment": "positive"
    },
    {
      "title": "Thailand records current account surplus of $2.2 billion in July",
      "url": "https://www.channelnewsasia.com/business/thailand-records-current-account-surplus-22-billion-july-5321936",
      "source": "Channel News Asia",
      "region": "North America",
      "published": "2025-08-29T15:21:23+08:00",
      "sentiment": "neutral"
    },
    {
      "title": "Tsitsipas upset by underarm serves as he slumps out of US Open",
      "url": "https://www.channelnewsasia.com/sport/tsitsipas-upset-underarm-serves-he-slumps-out-us-open-5321931",
      "source": "Channel News Asia",
      "region": "North America",
      "published": "2025-08-29T15:19:18+08:00",
      "sentiment": "negative"
    },
    {
      "title": "Thai PM Paetongtarn faces verdict in court case seeking her removal",
      "url": "https://www.channelnewsasia.com/asia/thai-pm-paetongtarn-shinawatra-court-verdict-live-5319566",
      "source": "Channel News Asia",
      "region": "North America",
      "published": "2025-08-29T15:00:47+08:00",
      "sentiment": "negative"
    },
    {
      "title": "Road traffic accidents up in the first half of 2025",
      "url": "https://www.channelnewsasia.com/singapore/road-traffic-accidents-first-half-2025-police-5317416",
      "source": "Channel News Asia",
      "region": "Global",
      "published": "2025-08-29T15:00:00+08:00",
      "sentiment": "negative"
    },
    {
      "title": "Injuries, deaths on Singapore\u2019s roads rise in H1 2025; accidents due to red-light violations also up",
      "url": "https://www.straitstimes.com/singapore/injuries-deaths-on-singapores-roads-rise-in-h1-2025-accidents-due-to-red-light-violation-also-up",
      "source": "Straits Times",
      "region": "Asia-Pacific",
      "published": "2025-08-29T15:00:00+08:00",
      "sentiment": "negative"
    },
    {
      "title": "Thai court begins reading verdict on fate of PM Paetongtarn",
      "url": "https://www.channelnewsasia.com/asia/thai-pm-paetongtarn-shinawatra-court-verdict-live-5319566",
      "source": "Channel News Asia",
      "region": "North America",
      "published": "2025-08-29T15:00:00+08:00",
      "sentiment": "negative"
    },
    {
      "title": "Indonesia's trade surplus seen at $3.2 billion in July as imports decline: Reuters poll",
      "url": "https://www.channelnewsasia.com/business/indonesias-trade-surplus-seen-32-billion-july-imports-decline-reuters-poll-5321896",
      "source": "Channel News Asia",
      "region": "North America",
      "published": "2025-08-29T14:50:29+08:00",
      "sentiment": "neutral"
    },
    {
      "title": "Two taken to hospital after multi-vehicle accident on CTE",
      "url": "https://www.straitstimes.com/singapore/two-taken-to-hospital-after-multi-vehicle-accident-on-cte",
      "source": "Straits Times",
      "region": "Global",
      "published": "2025-08-29T14:50:00+08:00",
      "sentiment": "negative"
    },
    {
      "title": "Indonesia's trade surplus seen at US$3.2 billion in July as imports decline: Reuters poll",
      "url": "https://www.channelnewsasia.com/business/indonesias-trade-surplus-seen-us32-billion-july-imports-decline-reuters-poll-5321896",
      "source": "Channel News Asia",
      "region": "North America",
      "published": "2025-08-29T14:50:00+08:00",
      "sentiment": "neutral"
    },
    {
      "title": "Binance says all futures trading is temporarily unavailable",
      "url": "https://www.channelnewsasia.com/business/binance-says-all-futures-trading-temporarily-unavailable-5321891",
      "source": "Channel News Asia",
      "region": "Global",
      "published": "2025-08-29T14:46:53+08:00",
      "sentiment": "neutral"
    },
    {
      "title": "Binance resumes futures trading after brief pause",
      "url": "https://www.channelnewsasia.com/business/binance-resumes-futures-trading-after-brief-pause-5321891",
      "source": "Channel News Asia",
      "region": "North America",
      "published": "2025-08-29T14:46:53+08:00",
      "sentiment": "neutral"
    },
    {
      "title": "India's powerful Hindu group chief urges three-child families as fertility rates fall",
      "url": "https://www.channelnewsasia.com/asia/indias-powerful-hindu-group-chief-urges-three-child-families-fertility-rates-fall-5321851",
      "source": "Channel News Asia",
      "region": "Asia-Pacific",
      "published": "2025-08-29T14:44:00+08:00",
      "sentiment": "positive"
    },
    {
      "title": "Viewers puzzled why character of Singaporean businessman on US TV series Countdown portrayed as only Malay-speaking",
      "url": "https://www.channelnewsasia.com/entertainment/prime-video-countdown-singaporean-businessman-speaks-only-malay-5321846",
      "source": "Channel News Asia",
      "region": "Asia-Pacific",
      "published": "2025-08-29T14:27:02+08:00",
      "sentiment": "negative"
    },
    {
      "title": "China's factory activity seen shrinking again on soft demand, job woes: Reuters poll",
      "url": "https://www.channelnewsasia.com/business/chinas-factory-activity-seen-shrinking-again-soft-demand-job-woes-reuters-poll-5321836",
      "source": "Channel News Asia",
      "region": "Asia-Pacific",
      "published": "2025-08-29T14:15:20+08:00",
      "sentiment": "negative"
    },
    {
      "title": "Political discourse is turning toxic, violent; parties must stick to their principles: Mayawati",
      "url": "https://www.thehindu.com/news/national/political-discourse-is-turning-toxic-violent-parties-must-stick-to-their-principles-mayawati/article69988263.ece",
      "source": "The Hindu",
      "region": "North America",
      "published": "2025-08-29T14:14:04+05:30",
      "sentiment": "positive"
    },
    {
      "title": "Eight injured in fire triggered by cylinder explosion in Badami in Karnataka",
      "url": "https://www.thehindu.com/news/national/karnataka/eight-injured-in-fire-triggered-by-cylinder-explosion-in-badami-in-karnataka/article69988241.ece",
      "source": "The Hindu",
      "region": "Asia-Pacific",
      "published": "2025-08-29T14:07:59+05:30",
      "sentiment": "negative"
    },
    {
      "title": "Watch: Amit Shah: Northeast moving from violence to peace and development",
      "url": "https://www.thehindu.com/shorts/watch-amit-shah-northeast-moving-from-violence-to-peace-and-development/article69988295.ece",
      "source": "The Hindu",
      "region": "Asia-Pacific",
      "published": "2025-08-29T14:06:59+05:30",
      "sentiment": "negative"
    },
    {
      "title": "Bihar SIR: SC agrees to hear RJD, CPI(ML)\u2019s plea to extend deadline for filing claims to September 15",
      "url": "https://www.thehindu.com/elections/bihar-assembly/bihar-sir-supreme-court-agrees-to-hear-plea-by-rjd-other-parties-to-extend-deadline-for-filing-claims-to-september-15/article69988232.ece",
      "source": "The Hindu",
      "region": "North America",
      "published": "2025-08-29T14:05:44+05:30",
      "sentiment": "positive"
    },
    {
      "title": "Watch: \u2018We don\u2019t support tariffs\u2019: Australian Foreign Minister Penny Wong",
      "url": "https://www.thehindu.com/shorts/watch-we-dont-support-tariffs-australian-foreign-minister-penny-wong/article69988272.ece",
      "source": "The Hindu",
      "region": "Asia-Pacific",
      "published": "2025-08-29T14:04:05+05:30",
      "sentiment": "positive"
    },
    {
      "title": "Watch: Justices Alok Aradhe and Vipul Pancholi sworn in amid Collegium dissent",
      "url": "https://www.thehindu.com/shorts/watch-justices-alok-aradhe-and-vipul-pancholi-sworn-in-amid-collegium-dissent/article69988268.ece",
      "source": "The Hindu",
      "region": "North America",
      "published": "2025-08-29T14:02:51+05:30",
      "sentiment": "neutral"
    },
    {
      "title": "Watch: India celebrates National Sports Day 2025 with three-day Jan Andolan",
      "url": "https://www.thehindu.com/shorts/watch-india-celebrates-national-sports-day-2025-with-three-day-jan-andolan/article69988255.ece",
      "source": "The Hindu",
      "region": "Asia-Pacific",
      "published": "2025-08-29T13:58:33+05:30",
      "sentiment": "positive"
    },
    {
      "title": "Watch: Japanese artists welcome PM Modi with dances and chants of the Gayatri Mantra",
      "url": "https://www.thehindu.com/shorts/watch-japanese-artists-welcome-pm-modi-with-dances-and-chants-of-the-gayatri-mantra/article69988247.ece",
      "source": "The Hindu",
      "region": "Asia-Pacific",
      "published": "2025-08-29T13:51:08+05:30",
      "sentiment": "positive"
    },
    {
      "title": "Jakarta protest: Indonesia President Prabowo expresses shock at \u2018excessive police actions\u2019 after delivery rider's death, calls for probe",
      "url": "https://www.channelnewsasia.com/asia/indonesia-jakarta-protest-gojek-ojol-rider-killed-pejompongan-prabowo-5321796",
      "source": "Channel News Asia",
      "region": "Asia-Pacific",
      "published": "2025-08-29T13:32:00+08:00",
      "sentiment": "negative"
    },
    {
      "title": "Jakarta protest: President Prabowo expresses shock at \u2018excessive police actions\u2019 after delivery rider's death, calls for probe",
      "url": "https://www.channelnewsasia.com/asia/indonesia-jakarta-protest-gojek-ojol-rider-killed-pejompongan-prabowo-5321796",
      "source": "Channel News Asia",
      "region": "Global",
      "published": "2025-08-29T13:32:00+08:00",
      "sentiment": "negative"
    },
    {
      "title": "Amid Trump\u2019s tariffs, India buys more US oil - competitive prices at play",
      "url": "https://timesofindia.indiatimes.com/business/india-business/amidst-donald-trumps-tariffs-india-buys-more-us-oil-competitive-prices-at-play-trade-deficit-to-narrow/articleshow/123578945.cms",
      "source": "Times of India",
      "region": "Asia-Pacific",
      "published": "2025-08-29T13:23:56+05:30",
      "sentiment": "negative"
    },
    {
      "title": "Bronco test: Rohit Sharma to report to BCCI's CoE on Sept 13; undergo fitness tests",
      "url": "https://timesofindia.indiatimes.com/sports/cricket/news/rohit-sharma-to-report-to-bccis-coe-on-september-13-for-fitness-tests/articleshow/123580008.cms",
      "source": "Times of India",
      "region": "Asia-Pacific",
      "published": "2025-08-29T13:22:07+05:30",
      "sentiment": "positive"
    },
    {
      "title": "Former Wildlife Reserves Singapore employee guilty of receiving bribe from engineering firm director",
      "url": "https://www.channelnewsasia.com/singapore/wildlife-reserves-assistant-director-corruption-bribe-engineering-firm-5321776",
      "source": "Channel News Asia",
      "region": "Asia-Pacific",
      "published": "2025-08-29T13:19:51+08:00",
      "sentiment": "negative"
    },
    {
      "title": "Cathay Cineplexes operator mm2 Asia reports group net loss of S$122.4 million on second half woes",
      "url": "https://www.channelnewsasia.com/business/cathay-cineplexes-cinema-operator-owner-mm2-asia-group-net-loss-surge-fiscal-year-2025-5321766",
      "source": "Channel News Asia",
      "region": "Global",
      "published": "2025-08-29T13:19:36+08:00",
      "sentiment": "negative"
    },
    {
      "title": "Operation Sindoor a golden chapter in humanity's victory against terrorism: President",
      "url": "https://www.thehindu.com/news/national/operation-sindoor-a-golden-chapter-in-humanitys-victory-against-terrorism-president/article69988198.ece",
      "source": "The Hindu",
      "region": "Asia-Pacific",
      "published": "2025-08-29T13:17:45+05:30",
      "sentiment": "negative"
    },
    {
      "title": "RJD, AIMIM move Supreme Court seeking extension of September 1 deadline for claim filing in Bihar SIR",
      "url": "https://www.thehindu.com/elections/bihar-assembly/rjd-aimim-move-supreme-court-seeking-extension-of-september-1-deadline-for-claim-filing-in-bihar-sir/article69988173.ece",
      "source": "The Hindu",
      "region": "Asia-Pacific",
      "published": "2025-08-29T13:16:50+05:30",
      "sentiment": "positive"
    },
    {
      "title": "\u2018Won\u2019t bow\u2019: Piyush Goyal\u2019s message amid US tariffs; calls for self-reliance",
      "url": "https://timesofindia.indiatimes.com/business/india-business/will-neither-bow-down-nor-appear-weak-piyush-goyal-on-trade-deals-with-india-message-amid-us-donald-trump-tariffs/articleshow/123580085.cms",
      "source": "Times of India",
      "region": "North America",
      "published": "2025-08-29T13:16:02+05:30",
      "sentiment": "positive"
    },
    {
      "title": "Hamburgini shuts down: Court orders liquidation after food poisoning scandal",
      "url": "https://timesofindia.indiatimes.com/world/middle-east/saudi-arabias-top-local-burger-chain-hamburgini-crashes-into-bankruptcy-shuts-down-operations/articleshow/123528752.cms",
      "source": "Times of India",
      "region": "North America",
      "published": "2025-08-29T13:15:55+05:30",
      "sentiment": "negative"
    },
    {
      "title": "T.N. illegal kidney sale racket: Madras High Court orders inquiry by Health Secretary",
      "url": "https://www.thehindu.com/news/national/tamil-nadu/tn-illegal-kidney-sale-racket-madras-high-court-orders-inquiry-by-health-secretary/article69987891.ece",
      "source": "The Hindu",
      "region": "North America",
      "published": "2025-08-29T13:05:34+05:30",
      "sentiment": "neutral"
    },
    {
      "title": "Motorcyclist taken to hospital after accident with private bus on AYE",
      "url": "https://www.straitstimes.com/singapore/motorcyclist-taken-to-hospital-after-accident-with-private-bus-on-aye",
      "source": "Straits Times",
      "region": "North America",
      "published": "2025-08-29T13:03:00+08:00",
      "sentiment": "negative"
    },
    {
      "title": "Pasir Panjang Wholesale Centre to rectify all fire safety issues to secure lease extension beyond 2026: SFA",
      "url": "https://www.channelnewsasia.com/singapore/pasir-panjang-wholesale-centre-lease-sfa-5321496",
      "source": "Channel News Asia",
      "region": "Asia-Pacific",
      "published": "2025-08-29T13:00:00+08:00",
      "sentiment": "positive"
    },
    {
      "title": "Pasir Panjang Wholesale Centre shops must comply with fire safety rules to secure lease extension",
      "url": "https://www.straitstimes.com/singapore/environment/pasir-panjang-wholesale-centre-shops-must-comply-with-fire-safety-rules-to-secure-lease-extension",
      "source": "Straits Times",
      "region": "North America",
      "published": "2025-08-29T13:00:00+08:00",
      "sentiment": "positive"
    },
    {
      "title": "39-yr-old cardiac surgeon dies of heart attack: CMC Vellore doc lists top causes of heart risk",
      "url": "https://timesofindia.indiatimes.com/life-style/health-fitness/health-news/39-year-old-chennai-surgeon-dies-of-heart-attack-cmc-vellore-doctor-lists-top-causes-of-heart-risk-in-young-working-professionals/articleshow/123578762.cms",
      "source": "Times of India",
      "region": "North America",
      "published": "2025-08-29T13:00:00+05:30",
      "sentiment": "positive"
    },
    {
      "title": "US Open day five",
      "url": "https://www.channelnewsasia.com/sport/us-open-day-five-5321791",
      "source": "Channel News Asia",
      "region": "North America",
      "published": "2025-08-29T12:59:13+08:00",
      "sentiment": "neutral"
    },
    {
      "title": "The August 2000 deluge that Hyderabad forgot",
      "url": "https://www.thehindu.com/news/national/telangana/the-august-2000-deluge-that-hyderabad-forgot/article69985423.ece",
      "source": "The Hindu",
      "region": "North America",
      "published": "2025-08-29T12:57:06+05:30",
      "sentiment": "negative"
    },
    {
      "title": "Starship lands in ocean: Reusable rocket milestone reached with historic splashdown",
      "url": "https://timesofindia.indiatimes.com/science/its-not-a-movie-its-spacex-elon-musk-shares-stunning-visuals-of-reusable-starship-splashdown/articleshow/123579586.cms",
      "source": "Times of India",
      "region": "North America",
      "published": "2025-08-29T12:52:35+05:30",
      "sentiment": "positive"
    },
    {
      "title": "Half of top-100 IIT rankers trained in Kota, every fourth admission linked to coaching hub",
      "url": "https://www.thehindu.com/education/colleges/half-of-top-100-iit-rankers-trained-in-kota-every-fourth-admission-linked-to-coaching-hub/article69988107.ece",
      "source": "The Hindu",
      "region": "Asia-Pacific",
      "published": "2025-08-29T12:48:30+05:30",
      "sentiment": "neutral"
    },
    {
      "title": "Qatar wants to negotiate trade pact with India: Goyal",
      "url": "https://www.thehindu.com/news/national/qatar-wants-to-negotiate-trade-pact-with-india-goyal/article69988112.ece",
      "source": "The Hindu",
      "region": "Asia-Pacific",
      "published": "2025-08-29T12:46:37+05:30",
      "sentiment": "positive"
    },
    {
      "title": "India's education cost: How much are families paying for fees, books, coaching?",
      "url": "https://timesofindia.indiatimes.com/education/news/how-much-do-indian-parents-spend-on-school-education-heres-what-the-nss-2025-survey-shows/articleshow/123579149.cms",
      "source": "Times of India",
      "region": "Asia-Pacific",
      "published": "2025-08-29T12:40:26+05:30",
      "sentiment": "positive"
    },
    {
      "title": "In India, capital does not just grow, it multiplies: PM Modi in Tokyo",
      "url": "https://www.thehindu.com/news/national/pm-modi-japan-india-economic-forum-tokyo-august-29-2025/article69988070.ece",
      "source": "The Hindu",
      "region": "Asia-Pacific",
      "published": "2025-08-29T12:39:21+05:30",
      "sentiment": "neutral"
    },
    {
      "title": "Judge says victim \u2018absolutely right\u2019 to report stepdad for sex abuse; man gets over 16 years\u2019 jail",
      "url": "https://www.straitstimes.com/singapore/courts-crime/judge-says-victim-was-absolutely-right-to-report-stepfather-for-sex-abuse-jails-man-over-16-years",
      "source": "Straits Times",
      "region": "North America",
      "published": "2025-08-29T12:35:00+08:00",
      "sentiment": "negative"
    },
    {
      "title": "Elgar Parishad case: Supreme Court to hear bail plea of Surendra Gadling on September 3",
      "url": "https://www.thehindu.com/news/national/elgar-parishad-case-supreme-court-to-hear-bail-plea-of-surendra-gadling-on-september-3/article69988080.ece",
      "source": "The Hindu",
      "region": "North America",
      "published": "2025-08-29T12:33:49+05:30",
      "sentiment": "positive"
    },
    {
      "title": "Students repeatedly caught vaping will face up to 14 days' suspension, 3 strokes of the cane: Desmond Lee",
      "url": "https://www.channelnewsasia.com/singapore/students-caught-vaping-face-harsher-penalties-suspension-caning-5321651",
      "source": "Channel News Asia",
      "region": "North America",
      "published": "2025-08-29T12:31:00+08:00",
      "sentiment": "negative"
    },
    {
      "title": "India has turned into \u2018oil money laundromat for Kremlin\u2019: White House trade adviser Peter Navarro",
      "url": "https://www.thehindu.com/news/international/white-house-trade-adviser-peter-navarro-on-india-russia/article69988004.ece",
      "source": "The Hindu",
      "region": "Asia-Pacific",
      "published": "2025-08-29T12:29:29+05:30",
      "sentiment": "positive"
    },
    {
      "title": "Madras High Court allows appeal filed by Edappadi K. Palaniswami in AIADMK leadership dispute case",
      "url": "https://www.thehindu.com/news/national/tamil-nadu/madras-high-court-allows-appeal-filed-by-edappadi-k-palaniswami-in-party-leadership-dispute-case/article69987576.ece",
      "source": "The Hindu",
      "region": "North America",
      "published": "2025-08-29T12:26:49+05:30",
      "sentiment": "negative"
    },
    {
      "title": "Sri Lanka pick recovering Hasaranga for Asia Cup",
      "url": "https://www.channelnewsasia.com/sport/sri-lanka-pick-recovering-hasaranga-asia-cup-5321771",
      "source": "Channel News Asia",
      "region": "Global",
      "published": "2025-08-29T12:26:36+08:00",
      "sentiment": "neutral"
    },
    {
      "title": "Train and bus services to be extended during F1 weekend",
      "url": "https://www.straitstimes.com/singapore/train-and-bus-services-to-be-extended-during-f1-weekend",
      "source": "Straits Times",
      "region": "North America",
      "published": "2025-08-29T12:20:00+08:00",
      "sentiment": "neutral"
    },
    {
      "title": "Expect road closures in Marina Bay area from Oct 1-7 for F1 race; train, bus services to be extended",
      "url": "https://www.straitstimes.com/singapore/train-and-bus-services-to-be-extended-during-f1-weekend",
      "source": "Straits Times",
      "region": "North America",
      "published": "2025-08-29T12:20:00+08:00",
      "sentiment": "neutral"
    },
    {
      "title": "Expect road closures in Marina Bay, Padang area from Oct 1-7 for F1; extended train, bus services",
      "url": "https://www.straitstimes.com/singapore/train-and-bus-services-to-be-extended-during-f1-weekend",
      "source": "Straits Times",
      "region": "North America",
      "published": "2025-08-29T12:20:00+08:00",
      "sentiment": "neutral"
    },
    {
      "title": "Supreme Court issues notice to Centre on plea to declare \u2018Ram Setu\u2019 national monument",
      "url": "https://www.thehindu.com/news/national/supreme-court-issues-notice-to-centre-on-plea-to-declare-ram-setu-national-monument/article69988032.ece",
      "source": "The Hindu",
      "region": "North America",
      "published": "2025-08-29T12:16:05+05:30",
      "sentiment": "positive"
    },
    {
      "title": "Head of powerful US Senate armed services panel arrives in Taiwan to discuss defence",
      "url": "https://www.channelnewsasia.com/east-asia/head-powerful-us-senate-armed-service-panel-arrive-taiwan-china-defence-5321721",
      "source": "Channel News Asia",
      "region": "North America",
      "published": "2025-08-29T12:08:41+08:00",
      "sentiment": "positive"
    },
    {
      "title": "Powerful US senator arrives in Taiwan to discuss security",
      "url": "https://www.channelnewsasia.com/east-asia/head-powerful-us-senate-armed-service-panel-arrive-taiwan-china-defence-5321721",
      "source": "Channel News Asia",
      "region": "North America",
      "published": "2025-08-29T12:08:00+08:00",
      "sentiment": "positive"
    },
    {
      "title": "'Already registered': R Ashwin signs up for overseas cricket franchise league",
      "url": "https://timesofindia.indiatimes.com/sports/cricket/news/already-registered-r-ashwin-makes-big-revelation-about-future-says-he-wants-to-live-life-on-his-terms/articleshow/123578751.cms",
      "source": "Times of India",
      "region": "Asia-Pacific",
      "published": "2025-08-29T12:06:01+05:30",
      "sentiment": "positive"
    },
    {
      "title": "Issue censor certificate to Manushi after necessary cuts, orders Madras High Court",
      "url": "https://www.thehindu.com/news/national/tamil-nadu/issue-censor-certificate-to-manushi-after-necessary-cuts-orders-madras-high-court/article69987663.ece",
      "source": "The Hindu",
      "region": "North America",
      "published": "2025-08-29T12:05:04+05:30",
      "sentiment": "negative"
    },
    {
      "title": "Issue censor certificate to Tamil movie Manushi after necessary cuts: Madras High Court",
      "url": "https://www.thehindu.com/news/national/tamil-nadu/issue-censor-certificate-to-manushi-after-necessary-cuts-orders-madras-high-court/article69987663.ece",
      "source": "The Hindu",
      "region": "North America",
      "published": "2025-08-29T12:05:04+05:30",
      "sentiment": "negative"
    },
    {
      "title": "Indonesia central bank says it will remain active in FX market after rupiah dips 1%",
      "url": "https://www.channelnewsasia.com/business/indonesia-central-bank-says-it-will-remain-active-fx-market-after-rupiah-dips-1-5321711",
      "source": "Channel News Asia",
      "region": "Asia-Pacific",
      "published": "2025-08-29T11:57:57+08:00",
      "sentiment": "positive"
    },
    {
      "title": "Indonesia to remain active in FX market after rupiah slide, central bank says",
      "url": "https://www.channelnewsasia.com/business/indonesia-remain-active-fx-market-after-rupiah-slide-central-bank-says-5321711",
      "source": "Channel News Asia",
      "region": "Asia-Pacific",
      "published": "2025-08-29T11:57:57+08:00",
      "sentiment": "positive"
    },
    {
      "title": "Protest at Microsoft: Company fires 4 employees; workers received voicemails",
      "url": "https://timesofindia.indiatimes.com/technology/tech-news/microsoft-terminates-4-employees-for-israel-related-protests-group-claims-fired-employees-received-voicemails-saying-/articleshow/123578659.cms",
      "source": "Times of India",
      "region": "Middle East",
      "published": "2025-08-29T11:57:56+05:30",
      "sentiment": "negative"
    },
    {
      "title": "Judge Frank Caprio's death leaves mourners remembering his compassion that drew many online fans",
      "url": "https://www.channelnewsasia.com/entertainment/judge-frank-caprio-death-memorial-service-5319986",
      "source": "Channel News Asia",
      "region": "North America",
      "published": "2025-08-29T11:57:31+08:00",
      "sentiment": "positive"
    },
    {
      "title": "Row over abuse against PM Modi: BJP-Congress workers clash in Patna \u2014 Watch video",
      "url": "https://timesofindia.indiatimes.com/india/row-over-abuse-against-pm-modi-bjp-congress-workers-clash-in-patna-watch-video/articleshow/123578579.cms",
      "source": "Times of India",
      "region": "North America",
      "published": "2025-08-29T11:55:19+05:30",
      "sentiment": "negative"
    },
    {
      "title": "Heavy rains hit Uttarakhand; several people trapped, houses damaged in landslips",
      "url": "https://www.thehindu.com/news/national/uttarakhand/heavy-rains-hit-uttarakhand-several-people-trapped-houses-damaged-in-landslips/article69987939.ece",
      "source": "The Hindu",
      "region": "North America",
      "published": "2025-08-29T11:55:17+05:30",
      "sentiment": "negative"
    },
    {
      "title": "Bihar SIR: RJD moves SC for extension of Sept 1 deadline for filing claims; hearing next week",
      "url": "https://timesofindia.indiatimes.com/india/bihar-sir-row-rjd-moves-sc-for-extension-of-september-1-deadline-hearing-next-week/articleshow/123578557.cms",
      "source": "Times of India",
      "region": "Asia-Pacific",
      "published": "2025-08-29T11:54:07+05:30",
      "sentiment": "neutral"
    },
    {
      "title": "Former Indian central bank governor Urjit Patel appointed IMF executive director",
      "url": "https://www.channelnewsasia.com/business/former-indian-central-bank-governor-urjit-patel-appointed-imf-executive-director-5321706",
      "source": "Channel News Asia",
      "region": "Asia-Pacific",
      "published": "2025-08-29T11:53:06+08:00",
      "sentiment": "neutral"
    },
    {
      "title": "Bihar announces scheme to provide financial aid to women for starting employment venture",
      "url": "https://www.thehindu.com/elections/bihar-assembly/bihar-announces-scheme-to-provide-financial-aid-to-women-for-starting-employment-venture/article69987962.ece",
      "source": "The Hindu",
      "region": "Asia-Pacific",
      "published": "2025-08-29T11:51:03+05:30",
      "sentiment": "positive"
    },
    {
      "title": "Porsche opens new lifestyle retail concept at Jewel Changi Airport",
      "url": "https://www.channelnewsasia.com/obsessions/porsche-jewel-changi-airport-lifestyle-retail-space-singapore-5321631",
      "source": "Channel News Asia",
      "region": "North America",
      "published": "2025-08-29T11:50:00+08:00",
      "sentiment": "positive"
    },
    {
      "title": "232 people investigated for involvement in scams where victims lost $6.15 million",
      "url": "https://www.straitstimes.com/singapore/232-people-investigated-for-involvement-in-scams-where-victims-lost-6-15-million",
      "source": "Straits Times",
      "region": "North America",
      "published": "2025-08-29T11:50:00+08:00",
      "sentiment": "negative"
    },
    {
      "title": "Gold price prediction: What's the outlook for August 29?",
      "url": "https://timesofindia.indiatimes.com/business/india-business/gold-price-prediction-today-what-is-the-gold-rate-outlook-for-august-29-2025-should-you-buy-or-sell-mcx-gold/articleshow/123577853.cms",
      "source": "Times of India",
      "region": "North America",
      "published": "2025-08-29T11:45:00+05:30",
      "sentiment": "positive"
    },
    {
      "title": "Amit Shah to launch BJP\u2019s 2026 Assam poll campaign through panchayat leaders\u2019 convention",
      "url": "https://www.thehindu.com/news/national/assam/amit-shah-to-launch-bjps-2026-assam-poll-campaign-through-panchayat-leaders-convention/article69987879.ece",
      "source": "The Hindu",
      "region": "Asia-Pacific",
      "published": "2025-08-29T11:41:00+05:30",
      "sentiment": "positive"
    },
    {
      "title": "Brazil mulls reprisals for 50% Trump tariffs: Sources",
      "url": "https://www.channelnewsasia.com/world/brazil-mulls-us-trump-tariffs-retaliation-trade-5321661",
      "source": "Channel News Asia",
      "region": "South America",
      "published": "2025-08-29T11:38:00+08:00",
      "sentiment": "neutral"
    },
    {
      "title": "Karnataka: Rain havoc leads to waterlogging, traffic congestion in Bengaluru on August 28",
      "url": "https://www.thehindu.com/news/national/karnataka/karnataka-rain-havoc-leads-to-waterlogging-traffic-congestion-in-bengaluru-on-august-28/article69985276.ece",
      "source": "The Hindu",
      "region": "North America",
      "published": "2025-08-29T11:35:48+05:30",
      "sentiment": "negative"
    },
    {
      "title": "Gauff embraces moment of vulnerability en route to US Open third round",
      "url": "https://www.channelnewsasia.com/sport/gauff-embraces-moment-vulnerability-en-route-us-open-third-round-5321686",
      "source": "Channel News Asia",
      "region": "North America",
      "published": "2025-08-29T11:33:41+08:00",
      "sentiment": "negative"
    },
    {
      "title": "Jerry Jones shifts tone: From \u2018I love you\u2019 to trade talk",
      "url": "https://timesofindia.indiatimes.com/sports/nfl/news/dallas-cowboys-owner-jerry-jones-shifted-his-stance-from-i-love-you-to-micahparsons-could-bring-a-lot-of-resources-in-a-trade/articleshow/123577980.cms",
      "source": "Times of India",
      "region": "Asia-Pacific",
      "published": "2025-08-29T11:32:49+05:30",
      "sentiment": "positive"
    },
    {
      "title": "Musk seeks dismissal of SEC's lawsuit regarding his 2022 Twitter stake",
      "url": "https://www.channelnewsasia.com/business/musk-seeks-dismissal-secs-lawsuit-regarding-his-2022-twitter-stake-5321671",
      "source": "Channel News Asia",
      "region": "North America",
      "published": "2025-08-29T11:31:09+08:00",
      "sentiment": "negative"
    },
    {
      "title": "Musk seeks dismissal of SEC lawsuit on his 2022 Twitter stake",
      "url": "https://www.channelnewsasia.com/business/musk-seeks-dismissal-sec-lawsuit-his-2022-twitter-stake-5321671",
      "source": "Channel News Asia",
      "region": "North America",
      "published": "2025-08-29T11:31:09+08:00",
      "sentiment": "negative"
    },
    {
      "title": "1291 PR roads damaged in rains in North Telangana",
      "url": "https://www.thehindu.com/news/national/telangana/1291-pr-roads-damaged-in-rains-in-north-telangana/article69987873.ece",
      "source": "The Hindu",
      "region": "Asia-Pacific",
      "published": "2025-08-29T11:25:29+05:30",
      "sentiment": "negative"
    },
    {
      "title": "Karnataka rain: Crops on over 61,000 hectares lost to heavy rainfall, floods in Belagavi district",
      "url": "https://www.thehindu.com/news/national/karnataka/karnataka-rain-crops-on-over-61000-hectares-lost-to-heavy-rainfall-floods-in-belagavi-district/article69985221.ece",
      "source": "The Hindu",
      "region": "Asia-Pacific",
      "published": "2025-08-29T11:23:18+05:30",
      "sentiment": "negative"
    },
    {
      "title": "South Korea's ex-first lady Kim Keon Hee indicted on bribery charges",
      "url": "https://www.channelnewsasia.com/east-asia/south-korea-ex-first-lady-kim-keon-hee-indicted-bribery-charges-5321531",
      "source": "Channel News Asia",
      "region": "Asia-Pacific",
      "published": "2025-08-29T11:20:00+08:00",
      "sentiment": "negative"
    },
    {
      "title": "Darbhanga Police arrests man accused of hurling abuses at PM Modi in Bihar",
      "url": "https://www.thehindu.com/news/national/bihar/darbhanga-police-arrests-man-accused-of-hurling-abuses-at-pm-modi-in-bihar/article69987831.ece",
      "source": "The Hindu",
      "region": "North America",
      "published": "2025-08-29T11:18:26+05:30",
      "sentiment": "negative"
    },
    {
      "title": "Police arrest man for abusive language against PM Modi during Voter Adhikar Yatra; Amit Shah demands apology from Rahul Gandhi",
      "url": "https://www.thehindu.com/news/national/bihar/darbhanga-police-arrests-man-accused-of-hurling-abuses-at-pm-modi-in-bihar/article69987831.ece",
      "source": "The Hindu",
      "region": "North America",
      "published": "2025-08-29T11:18:26+05:30",
      "sentiment": "negative"
    },
    {
      "title": "NRI lauded by Pawan Kalyan for writing book on A.P. politics",
      "url": "https://www.thehindu.com/news/national/andhra-pradesh/nri-lauded-by-pawan-kalyan-for-writing-book-on-ap-politics/article69985051.ece",
      "source": "The Hindu",
      "region": "Asia-Pacific",
      "published": "2025-08-29T11:15:33+05:30",
      "sentiment": "neutral"
    },
    {
      "title": "\u2018Draconian tariffs\u2019: Chris Wood sees $55-6bn hit for India",
      "url": "https://timesofindia.indiatimes.com/business/india-business/draconian-tariffs-chris-wood-sees-55-60-billion-hit-for-india-calls-it-trumps-personal-pique/articleshow/123577272.cms",
      "source": "Times of India",
      "region": "Asia-Pacific",
      "published": "2025-08-29T11:09:29+05:30",
      "sentiment": "negative"
    },
    {
      "title": "Congress legislators express solidarity with farmers in Kalaburagi district of Karnataka, seek \u20b9341 crore crop insurance",
      "url": "https://www.thehindu.com/news/national/karnataka/congress-legislators-express-solidarity-with-farmers-in-kalaburagi-district-of-karnataka-seek-341-crore-crop-insurance/article69985285.ece",
      "source": "The Hindu",
      "region": "Asia-Pacific",
      "published": "2025-08-29T11:08:24+05:30",
      "sentiment": "positive"
    },
    {
      "title": "WADA slams 'ill-conceived' Enhanced Games after named in lawsuit",
      "url": "https://www.channelnewsasia.com/sport/wada-slams-ill-conceived-enhanced-games-after-named-lawsuit-5321621",
      "source": "Channel News Asia",
      "region": "Global",
      "published": "2025-08-29T11:08:19+08:00",
      "sentiment": "negative"
    },
    {
      "title": "Taiwan estimates China spent 40% more on Pacific drills last year to hit US$21 billion",
      "url": "https://www.channelnewsasia.com/east-asia/taiwan-estimates-china-spent-more-pacific-drills-21-billion-5321606",
      "source": "Channel News Asia",
      "region": "North America",
      "published": "2025-08-29T11:06:23+08:00",
      "sentiment": "neutral"
    },
    {
      "title": "Theatre director Deepan Sivaraman on Ibsen\u2019s \u2018Peer Gynt\u2019 adaptation to be staged at Alexandrinsky Theatre Festival in Russia",
      "url": "https://www.thehindu.com/entertainment/theatre/theatre-director-deepan-sivaraman-on-ibsens-peer-gynt-adaptation-at-alexandrinsky-theatre-festival-russia/article69984156.ece",
      "source": "The Hindu",
      "region": "North America",
      "published": "2025-08-29T11:00:00+05:30",
      "sentiment": "positive"
    },
    {
      "title": "Justices Alok Aradhe and Vipul M. Pancholi sworn in as Supreme Court Judges",
      "url": "https://www.thehindu.com/news/national/justices-alok-aradhe-and-vipul-m-pancholi-sworn-in-as-supreme-court-judges/article69987812.ece",
      "source": "The Hindu",
      "region": "North America",
      "published": "2025-08-29T10:56:04+05:30",
      "sentiment": "positive"
    }
  ]
}